tufw/__init__.py
tufw/firewall.py
tufw-1.1.2.dist-info/LICENSE
tufw-1.1.2.dist-info/METADATA
tufw-1.1.2.dist-info/WHEEL
tufw-1.1.2.dist-info/entry_points.txt
tufw-1.1.2.dist-info/top_level.txt
tufw-1.1.2.dist-info/RECORD
