Metadata-Version: 2.1
Name: tufw
Version: 1.1.2
Summary: Ufw terminal frontend based on dialog
Home-page: https://github.com/a13ssandr0/tufw
Author: Alessandro Campolo
Author-email: campoloalex@gmail.com
Project-URL: Bug Tracker, https://github.com/a13ssandr0/tufw/issues
Classifier: Programming Language :: Python :: 3
Classifier: License :: OSI Approved :: MIT License
Classifier: Operating System :: POSIX :: Linux
Requires-Python: >=3.0
License-File: LICENSE
Requires-Dist: pythondialog
